{"nodes": [{"id": "tray", "label": "tray.rs", "file_type": "code", "source_file": "src-tauri/src/desktops/tray.rs", "source_location": "L1"}, {"id": "tray_create_tray", "label": "create_tray()", "file_type": "code", "source_file": "src-tauri/src/desktops/tray.rs", "source_location": "L20"}], "edges": [{"source": "tray", "target": "tauri", "relation": "imports_from", "confidence": "EXTRACTED", "source_file": "src-tauri/src/desktops/tray.rs", "source_location": "L2", "weight": 1.0}, {"source": "tray", "target": "tauri", "relation": "imports_from", "confidence": "EXTRACTED", "source_file": "src-tauri/src/desktops/tray.rs", "source_location": "L8", "weight": 1.0}, {"source": "tray", "target": "tauri", "relation": "imports_from", "confidence": "EXTRACTED", "source_file": "src-tauri/src/desktops/tray.rs", "source_location": "L15", "weight": 1.0}, {"source": "tray", "target": "tray_create_tray", "relation": "contains", "confidence": "EXTRACTED", "source_file": "src-tauri/src/desktops/tray.rs", "source_location": "L20", "weight": 1.0}]}